Metadata-Version: 2.1
Name: vialink-utils-discovery
Version: 0.0.8
Summary: Vialink Utils
Home-page: 
Author: SSripilaipong
Author-email: santhapon@via.link
License: Apache 2.0
Requires-Python: >=3.7
